setup.py
cbmock/__init__.py
cbmock/connection.py
cbmock/views.py
py_mock_couchbase.egg-info/PKG-INFO
py_mock_couchbase.egg-info/SOURCES.txt
py_mock_couchbase.egg-info/dependency_links.txt
py_mock_couchbase.egg-info/top_level.txt
tests/__init__.py
tests/test_it_all.py