Metadata-Version: 1.0
Name: py-mock-couchbase
Version: 1.0.0
Summary: py-mock-couchbase
Home-page: https://github.com/SPSCommerce/py-mock-couchbase
Author: pjdecoursey
Author-email: webapps@spscommerce.com
License: MIT
Platform: UNKNOWN
